nwpc_hpc_model/__init__.py
nwpc_hpc_model/base/__init__.py
nwpc_hpc_model/base/query_category.py
nwpc_hpc_model/base/query_item.py
nwpc_hpc_model/base/query_model.py
nwpc_hpc_model/base/query_property.py
nwpc_hpc_model/base/record_parser.py
nwpc_hpc_model/base/value_saver.py
nwpc_hpc_model/disk_space/__init__.py
nwpc_hpc_model/disk_space/aix/__init__.py
nwpc_hpc_model/disk_space/aix/query_category.py
nwpc_hpc_model/disk_space/aix/query_model.py
nwpc_hpc_model/disk_space/pi/__init__.py
nwpc_hpc_model/disk_space/pi/query_category.py
nwpc_hpc_model/disk_space/pi/query_model.py
nwpc_hpc_model/disk_usage/__init__.py
nwpc_hpc_model/disk_usage/aix/__init__.py
nwpc_hpc_model/disk_usage/aix/query_category.py
nwpc_hpc_model/disk_usage/aix/query_model.py
nwpc_hpc_model/disk_usage/pi/__init__.py
nwpc_hpc_model/disk_usage/pi/query_category.py
nwpc_hpc_model/disk_usage/pi/query_model.py
nwpc_hpc_model/workload/__init__.py
nwpc_hpc_model/workload/filter.py
nwpc_hpc_model/workload/filter_condition.py
nwpc_hpc_model/workload/loadleveler/__init__.py
nwpc_hpc_model/workload/loadleveler/query_model.py
nwpc_hpc_model/workload/loadleveler/record_parser.py
nwpc_hpc_model/workload/loadleveler/value_saver.py
nwpc_hpc_model/workload/slurm/__init__.py
nwpc_hpc_model/workload/slurm/slurm_query_category.py
nwpc_hpc_model/workload/slurm/slurm_query_model.py
tests/disk_space/__init__.py
tests/disk_space/aix/__init__.py
tests/disk_space/aix/query_model/__init__.py
tests/disk_space/aix/query_model/test_df_g.py
tests/disk_space/pi/__init__.py
tests/disk_space/pi/query_model/__init__.py
tests/disk_space/pi/query_model/test_df_m.py
tests/disk_usage/__init__.py
tests/disk_usage/aix/__init__.py
tests/disk_usage/aix/query_model/__init__.py
tests/disk_usage/aix/query_model/test_quotainfo.py
tests/disk_usage/pi/__init__.py
tests/disk_usage/pi/query_model/__init__.py
tests/disk_usage/pi/query_model/test_quotainfo.py
tests/workload/__init__.py
tests/workload/test_record_parser.py
nwpc_hpc_model-0.3.2.dist-info/LICENSE
nwpc_hpc_model-0.3.2.dist-info/METADATA
nwpc_hpc_model-0.3.2.dist-info/WHEEL
nwpc_hpc_model-0.3.2.dist-info/top_level.txt
nwpc_hpc_model-0.3.2.dist-info/RECORD
