Metadata-Version: 2.1
Name: nwpc-hpc-model
Version: 0.3.2
Summary: A collection of models for HPC used in NWPC.
Home-page: https://github.com/perillaroc/nwpc-hpc-model
Author: perillaroc
Author-email: perillaroc@gmail.com
License: GPL-3.0
Keywords: nwpc hpc model
Platform: UNKNOWN
Classifier: Development Status :: 2 - Pre-Alpha
Classifier: Intended Audience :: Developers
Classifier: License :: OSI Approved :: MIT License
Classifier: Programming Language :: Python :: 3.6
Classifier: Programming Language :: Python :: 3.7
Provides-Extra: cov
Requires-Dist: pytest-cov ; extra == 'cov'
Requires-Dist: codecov ; extra == 'cov'
Provides-Extra: test
Requires-Dist: pyyaml ; extra == 'test'
Requires-Dist: pytest ; extra == 'test'
Requires-Dist: pytest-cov ; extra == 'test'
Requires-Dist: codecov ; extra == 'test'
